simplejwt_sso/__init__.py
simplejwt_sso/admin.py
simplejwt_sso/apps.py
simplejwt_sso/authentication.py
simplejwt_sso/models.py
simplejwt_sso/serializers.py
simplejwt_sso/tests.py
simplejwt_sso/views.py
simplejwt_sso/migrations/__init__.py
djangorestframework_simplejwt_sso-1.0.1.dist-info/LICENSE
djangorestframework_simplejwt_sso-1.0.1.dist-info/METADATA
djangorestframework_simplejwt_sso-1.0.1.dist-info/WHEEL
djangorestframework_simplejwt_sso-1.0.1.dist-info/top_level.txt
djangorestframework_simplejwt_sso-1.0.1.dist-info/RECORD
