Metadata-Version: 2.1
Name: djangorestframework-simplejwt-sso
Version: 1.0.1
Summary: A minimal JSON Web Token authentication to allow sso
Home-page: https://www.example.com/
Author: Parick Nderitu
Author-email: nderitupatrick4@gmail.com
License: MIT
Platform: UNKNOWN
Classifier: Environment :: Web Environment
Classifier: Framework :: Django
Classifier: Intended Audience :: Developers
Classifier: License :: OSI Approved :: BSD License
Classifier: Operating System :: OS Independent
Classifier: Programming Language :: Python
Classifier: Programming Language :: Python :: 3
Classifier: Programming Language :: Python :: 3 :: Only
Classifier: Programming Language :: Python :: 3.6
Classifier: Programming Language :: Python :: 3.7
Classifier: Programming Language :: Python :: 3.8
Classifier: Topic :: Internet :: WWW/HTTP
Classifier: Topic :: Internet :: WWW/HTTP :: Dynamic Content
Requires-Dist: djangorestframework
Requires-Dist: djangorestframework-simplejwt
Requires-Dist: cryptography
